unhandled_exit/__init__.py
unhandled_exit-1.0.0.dist-info/METADATA
unhandled_exit-1.0.0.dist-info/WHEEL
unhandled_exit-1.0.0.dist-info/licenses/LICENSE
unhandled_exit-1.0.0.dist-info/RECORD
