Metadata-Version: 2.1
Name: unhandled_exit
Version: 1.0.0
Summary: Exit the whole process if any thread throws an unhandled exception
Project-URL: Source Code, https://github.com/rfjakob/unhandled_exit
Project-URL: Bug Tracker, https://github.com/rfjakob/unhandled_exit/issues
Author-email: Jakob Unterwurzacher <jakobunt@gmail.com>
License-File: LICENSE
Classifier: License :: OSI Approved :: MIT License
Classifier: Operating System :: OS Independent
Classifier: Programming Language :: Python :: 3
Classifier: Programming Language :: Python :: 3.8
Requires-Python: >=3.8
